esc_mini_tools_lib/__init__.py
esc_mini_tools_lib/_version.py
esc_mini_tools_lib/api.py
esc_mini_tools_lib/logger.py
esc_mini_tools_lib/paths.py
esc_mini_tools_lib/tools/__init__.py
esc_mini_tools_lib/tools/add_up_two_number.py
esc_mini_tools_lib/tools/chinese_to_english_punctuation.py
esc_mini_tools_lib/tools/confluence_export.py
esc_mini_tools_lib/tools/count_llm_token.py
esc_mini_tools_lib/typehint.py
esc_mini_tools_lib/vendor/__init__.py
esc_mini_tools_lib/vendor/pytest_cov_helper.py
esc_mini_tools_lib-0.1.8.dist-info/AUTHORS.rst
esc_mini_tools_lib-0.1.8.dist-info/LICENSE.txt
esc_mini_tools_lib-0.1.8.dist-info/METADATA
esc_mini_tools_lib-0.1.8.dist-info/WHEEL
esc_mini_tools_lib-0.1.8.dist-info/RECORD
