Metadata-Version: 2.3
Name: esc_mini_tools_lib
Version: 0.1.8
Summary: A reusable library of mini-tools with Pydantic-based APIs, designed for multi-platform deployment in web apps, serverless functions, and AI systems.
License: AGPL-3.0-or-later
Author: Sanhe Hu
Author-email: sanhehu@easyscalecloud.com
Maintainer: Sanhe Hu
Maintainer-email: sanhehu@easyscalecloud.com
Requires-Python: >=3.10,<4.0
Classifier: License :: OSI Approved :: GNU Affero General Public License v3 or later (AGPLv3+)
Classifier: Programming Language :: Python :: 3
Classifier: Programming Language :: Python :: 3.10
Classifier: Programming Language :: Python :: 3.11
Classifier: Programming Language :: Python :: 3.12
Classifier: Programming Language :: Python :: 3.13
Provides-Extra: auto
Provides-Extra: dev
Provides-Extra: doc
Provides-Extra: test
Requires-Dist: Sphinx (>=7.4.7,<8.0.0) ; extra == "doc"
Requires-Dist: atlas_doc_parser (>=0.1.2,<1.0.0)
Requires-Dist: boltons (>=25.0.0,<26.0.0)
Requires-Dist: boto-session-manager (>=1.8.1,<2.0.0)
Requires-Dist: boto3 (>=1.35.99,<2.0.0)
Requires-Dist: build (>=1.2.1,<2.0.0) ; extra == "dev"
Requires-Dist: docfly (==3.0.0) ; extra == "doc"
Requires-Dist: docpack (>=0.1.6,<1.0.0)
Requires-Dist: func-args (>=1.0.1,<2.0.0)
Requires-Dist: furo (==2024.8.6) ; extra == "doc"
Requires-Dist: ipython (>=8.18.1,<8.19.0) ; extra == "doc"
Requires-Dist: nbsphinx (>=0.8.12,<1.0.0) ; extra == "doc"
Requires-Dist: pydantic (>=2.12.0,<3.0.0)
Requires-Dist: pygments (>=2.18.0,<3.0.0) ; extra == "doc"
Requires-Dist: pytest (>=8.2.2,<9.0.0) ; extra == "test"
Requires-Dist: pytest-cov (>=6.0.0,<7.0.0) ; extra == "test"
Requires-Dist: rich (>=13.8.1,<14.0.0) ; extra == "dev"
Requires-Dist: rstobj (==1.2.1) ; extra == "doc"
Requires-Dist: s3pathlib (>=2.3.6,<3.0.0)
Requires-Dist: soft_deps (>=0.1.1,<1.0.0)
Requires-Dist: sphinx-copybutton (>=0.5.2,<1.0.0) ; extra == "doc"
Requires-Dist: sphinx-design (>=0.6.1,<1.0.0) ; extra == "doc"
Requires-Dist: sphinx-jinja (>=2.0.2,<3.0.0) ; extra == "doc"
Requires-Dist: tiktoken (>=0.12.0,<1.0.0)
Requires-Dist: twine (>=6.0.0,<7.0.0) ; extra == "dev"
Requires-Dist: vislog (>=0.1.2,<1.0.0)
Requires-Dist: wheel (>=0.45.0,<1.0.0) ; extra == "dev"
Project-URL: Changelog, https://github.com/easyscalecloud/esc_mini_tools_lib-project/blob/main/release-history.rst
Project-URL: Documentation, https://esc-mini-tools-lib.readthedocs.io/en/latest/
Project-URL: Download, https://pypi.org/pypi/esc-mini-tools-lib#files
Project-URL: Homepage, https://github.com/easyscalecloud/esc_mini_tools_lib-project
Project-URL: Issues, https://github.com/easyscalecloud/esc_mini_tools_lib-project/issues
Project-URL: Repository, https://github.com/easyscalecloud/esc_mini_tools_lib-project
